goroutine/__init__.py
goroutine/app.py
goroutine_py-1.0.9.dist-info/LICENSE
goroutine_py-1.0.9.dist-info/METADATA
goroutine_py-1.0.9.dist-info/WHEEL
goroutine_py-1.0.9.dist-info/top_level.txt
goroutine_py-1.0.9.dist-info/RECORD
