Metadata-Version: 2.1
Name: goroutine-py
Version: 1.0.9
Summary: An Asyncio-based concurrency library for Python.
Author-email: xudesoft <xudesoft@126.com>
Project-URL: Homepage, https://github.com/purplegrapeZz/goroutine-py
Project-URL: Issues, https://github.com/purplegrapeZz/goroutine-py/issues
Classifier: Programming Language :: Python :: 3
Classifier: License :: OSI Approved :: MIT License
Classifier: Operating System :: OS Independent
Requires-Python: >=3.7
License-File: LICENSE
